[
  {
    "date": "2025-10-01",
    "in": 195000,
    "out": 0,
    "desc": "USAMA Hj. Noneng Sumiaty 3 Bulan (Okt, Nov, Des)"
  },
  {
    "date": "2025-10-03",
    "in": 38000,
    "out": 0,
    "desc": "USAMA Teh Reni"
  },
  {
    "date": "2025-10-03",
    "in": 19000,
    "out": 0,
    "desc": "USAMA Wa Lilis"
  },
  {
    "date": "2025-10-04",
    "in": 38000,
    "out": 0,
    "desc": "USAMA Muhamad Hanif Muhsin"
  },
  {
    "date": "2025-10-04",
    "in": 19000,
    "out": 0,
    "desc": "USAMA Rikma Parlina"
  }
]
